plotune_sdk/__init__.py
plotune_sdk/models/__init__.py
plotune_sdk/models/config_models.py
plotune_sdk/models/file_models.py
plotune_sdk/models/variable_models.py
plotune_sdk/src/__init__.py
plotune_sdk/src/authenticator.py
plotune_sdk/src/core.py
plotune_sdk/src/forms.py
plotune_sdk/src/runtime.py
plotune_sdk/src/server.py
plotune_sdk/src/streams.py
plotune_sdk/src/workers/__init__.py
plotune_sdk/src/workers/consume_worker.py
plotune_sdk/src/workers/producer_worker.py
plotune_sdk/utils/__init__.py
plotune_sdk/utils/constants.py
plotune_sdk/utils/logger.py
plotune_sdk/utils/server_helpers.py
plotune_sdk-0.1.1.dist-info/licenses/LICENSE
plotune_sdk-0.1.1.dist-info/METADATA
plotune_sdk-0.1.1.dist-info/WHEEL
plotune_sdk-0.1.1.dist-info/top_level.txt
plotune_sdk-0.1.1.dist-info/RECORD
