Metadata-Version: 2.4
Name: plotune_sdk
Version: 0.1.1
Summary: Plotune SDK for developing extensions
Author-email: Plotune Team <contact@plotune.net>
License-Expression: Apache-2.0
Classifier: Development Status :: 3 - Alpha
Classifier: Intended Audience :: Developers
Classifier: Programming Language :: Python :: 3
Classifier: Programming Language :: Python :: 3.10
Classifier: Programming Language :: Python :: 3.11
Classifier: Programming Language :: Python :: 3.12
Classifier: Operating System :: OS Independent
Classifier: Topic :: Software Development :: Libraries :: Python Modules
Requires-Python: >=3.10
License-File: LICENSE
Requires-Dist: fastapi<1,>=0.100.0
Requires-Dist: uvicorn[standard]<1,>=0.20.0
Requires-Dist: httpx<1,>=0.24.0
Requires-Dist: pydantic<3,>=2.0.0
Requires-Dist: pillow<11,>=10.0.0
Requires-Dist: pystray<1,>=0.19.5
Requires-Dist: packaging<25,>=24.0
Requires-Dist: platformdirs<5,>=4.0.0
Requires-Dist: diskcache<6,>=5.6.3
Requires-Dist: aiohttp~=3.13
Provides-Extra: dev
Requires-Dist: pytest<8,>=7.0.0; extra == "dev"
Requires-Dist: ruff<1,>=0.1.0; extra == "dev"
Requires-Dist: black<24,>=23.0.0; extra == "dev"
Requires-Dist: mypy<2,>=1.0.0; extra == "dev"
Requires-Dist: pip-chill<2,>=1.0.0; extra == "dev"
Requires-Dist: pytest-asyncio<1,>=0.20.0; extra == "dev"
Requires-Dist: pytest-cov<5,>=4.0.0; extra == "dev"
Requires-Dist: types-httpx; extra == "dev"
Requires-Dist: types-pydantic; extra == "dev"
Requires-Dist: diskcache<6,>=5.6.3; extra == "dev"
Dynamic: license-file
